pokedex/__init__.py
pokedex/pokedex.py
pokedex.py-2.0.0.dist-info/LICENSE.txt
pokedex.py-2.0.0.dist-info/METADATA
pokedex.py-2.0.0.dist-info/WHEEL
pokedex.py-2.0.0.dist-info/top_level.txt
pokedex.py-2.0.0.dist-info/RECORD
