Metadata-Version: 2.1
Name: pokedex.py
Version: 2.0.0
Summary: Python wrapper library for the Pokédex API.
Home-page: https://github.com/PokeDevs/pokedex.py
Author: iamtraction
License: MIT
Keywords: pokemon pokedex api database pokeapi pokedb wrapper library
Classifier: Development Status :: 5 - Production/Stable
Classifier: License :: OSI Approved :: MIT License
Classifier: Intended Audience :: Developers
Classifier: Natural Language :: English
Classifier: Operating System :: OS Independent
Classifier: Programming Language :: Python
Classifier: Programming Language :: Python :: 2.7
Classifier: Programming Language :: Python :: 3.4
Classifier: Topic :: Internet
Classifier: Topic :: Software Development :: Libraries
Classifier: Topic :: Software Development :: Libraries :: Python Modules
Classifier: Topic :: Utilities
Requires-Python: >=2.7, !=3.0.*, !=3.1.*, !=3.2.*, !=3.3.*, <4
License-File: LICENSE.txt
Requires-Dist: requests <3.0.0,>=2.20.0
